{
   "id": "QWEUkzT_TOc",
    "channelId": "UCFZXu-bwN6kiE8F_6LhmR9Q",
    "title": "Review Spesifikasi Samsung Galaxy A9 Dan Harga Terbarunya !!",
    "description": "Sumber : hargahpgadget.comKeyword : HP Samsung Galaxy A9 , Handphone Samsung Galaxy A9 , Samsung Galaxy A9 , Review Samsung Galaxy A9 , Spesifikasi Samsung Galaxy A9  Terbaru, Spesifikasi Samsung Galaxy A9 , RAM Samsung Galaxy A9 , Kamera Samsung Galaxy A9 , Memori Samsung Galaxy A9 , Samsung Galaxy A9  Terbaru 2016",
    "channelTitle": "Rajanya Hape",
    "tags": [
     "Samsung Galaxy A9",
     "HP Samsung Galaxy A9",
     "Spesifikasi Samsung Galaxy A9",
     "Harga Samsung Galaxy A9"
    ],
   "statistics": {
    "viewCount": "6246",
    "likeCount": "9",
    "dislikeCount": "1",
    "favoriteCount": "0",
    "commentCount": "2"
   },
 "items": [
  {
      "authorDisplayName": "Zul Vahmi",
      "textDisplay": "gua pun mau tnyak gtu .. bingung gua",
	  "label": "off-topic"
  },
  {
      "authorDisplayName": "Kholiq 68",
      "textDisplay": "kalo ditanya mending milih samsung atau oppo dan knp?",
	  "label": "product-neutral"
  }
 ]
}